dltools/__init__.py
dltools/schema/__init__.py
dltools/schema/main.py
dltools/streaming/__init__.py
dltools/streaming/base.py
dltools2-0.0.1.dist-info/LICENSE
dltools2-0.0.1.dist-info/METADATA
dltools2-0.0.1.dist-info/WHEEL
dltools2-0.0.1.dist-info/top_level.txt
dltools2-0.0.1.dist-info/RECORD
