Metadata-Version: 2.1
Name: dltools2
Version: 0.0.1
Summary: Datalake Tools
Home-page: https://github.com/stonezhong/dltools
Author: Stone Zhong
Author-email: stonezhong@hotmail.com
License: MIT
Classifier: License :: OSI Approved :: MIT License
Classifier: Programming Language :: Python :: 3
License-File: LICENSE
Requires-Dist: jsonschema
